analiticcl-0.4.9.dist-info/METADATA
analiticcl-0.4.9.dist-info/WHEEL
analiticcl/__init__.py
analiticcl/analiticcl.cpython-310-aarch64-linux-gnu.so
analiticcl-0.4.9.dist-info/RECORD
