Metadata-Version: 2.4
Name: analiticcl
Version: 0.4.9
Requires-Dist: pytest ; extra == 'test'
Provides-Extra: test
Home-Page: https://github.com/proycon/analiticcl
